chmod/__init__.py
chmod/chmod.py
chmod-0.0.7.dist-info/LICENSE.txt
chmod-0.0.7.dist-info/METADATA
chmod-0.0.7.dist-info/WHEEL
chmod-0.0.7.dist-info/top_level.txt
chmod-0.0.7.dist-info/RECORD
