Metadata-Version: 2.1
Name: chmod
Version: 0.0.7
Summary: Basic chmod conversion tool
Author: Harry Sharma
Author-email: harrysharma1066@gmail.com
License-File: LICENSE.txt
